sphinx_thebe/__init__.py
sphinx_thebe/_version.py
sphinx_thebe/_static/play-solid.svg
sphinx_thebe/_static/sphinx-thebe.css
sphinx_thebe/_static/sphinx-thebe.js
sphinx_thebe-0.3.0.dist-info/METADATA
sphinx_thebe-0.3.0.dist-info/WHEEL
sphinx_thebe-0.3.0.dist-info/licenses/LICENSE
sphinx_thebe-0.3.0.dist-info/RECORD
